lctk/__init__.py
lctk/lctk.py
lctk-0.0.6.dist-info/LICENSE
lctk-0.0.6.dist-info/METADATA
lctk-0.0.6.dist-info/WHEEL
lctk-0.0.6.dist-info/top_level.txt
lctk-0.0.6.dist-info/RECORD
