Metadata-Version: 2.1
Name: lctk
Version: 0.0.6
Summary: A tool to create linked list, binary tree and graph from array or dictionary for the ease of local test. 
Home-page: https://github.com/chengyutang/lctk
Author: Chengyu Tang
Author-email: chyutang@gmail.com
License: UNKNOWN
Keywords: LeetCode
Platform: UNKNOWN
Classifier: Programming Language :: Python :: 3
Classifier: License :: OSI Approved :: MIT License
Classifier: Operating System :: OS Independent
